{  
  "type" : "module",
  "name": "green-light-backend",
  "description": "New Way of making connections. Time to increase the birth rate and save Korea.",
  "version": "1.0.0",
  "main": "index.js",
  "keywords": [],
  "author": "",
  "license": "ISC",
  "scripts": {
    "start": "node server.js",
    "dev": "nodemon --exec babel-node server"
  },
  "dependencies": {
    "@apollo/server": "^4.4.0",
    "@graphql-tools/load-files": "^6.6.1",
    "@graphql-tools/merge": "^8.3.18",
    "@graphql-tools/schema": "^9.0.16",
    "graphql": "^16.6.0"
  },
  "devDependencies": {
    "@babel/core": "^7.21.0",
    "@babel/node": "^7.20.7",
    "@babel/preset-env": "^7.20.2",
    "nodemon": "^2.0.20"
  }
}
